non_param_score_est/__init__.py
non_param_score_est/estimators/__init__.py
non_param_score_est/estimators/abstract.py
non_param_score_est/estimators/kde.py
non_param_score_est/estimators/landweber.py
non_param_score_est/estimators/nu_method.py
non_param_score_est/estimators/ssge.py
non_param_score_est/estimators/stein.py
non_param_score_est/estimators/tikhonov.py
non_param_score_est/matrix_kernels/__init__.py
non_param_score_est/matrix_kernels/abstract.py
non_param_score_est/matrix_kernels/curlfree_kernel.py
non_param_score_est/matrix_kernels/diagonal_kernel.py
non_param_score_est/matrix_kernels/utils.py
non_param_score_est/tests/__init__.py
non_param_score_est/tests/plots.py
non_param_score_est/tests/test_score_estimation.py
non_param_score_est-1.0.0.dist-info/LICENSE
non_param_score_est-1.0.0.dist-info/METADATA
non_param_score_est-1.0.0.dist-info/WHEEL
non_param_score_est-1.0.0.dist-info/top_level.txt
non_param_score_est-1.0.0.dist-info/zip-safe
non_param_score_est-1.0.0.dist-info/RECORD
