Metadata-Version: 2.1
Name: non-param-score-est
Version: 1.0.0
Summary: Non parametric score function estimation library
Home-page: https://github.com/krunolp/non_param_score_est
Author: Krunoslav Lehman Pavasovic
Author-email: krunolp@gmail.com
License: MIT
Project-URL: Source, https://github.com/krunolp/non_param_score_est
Project-URL: Tracker, https://github.com/krunolp/non_param_score_est/issues
Classifier: Development Status :: 5 - Production/Stable
Classifier: Environment :: MacOS X
Classifier: License :: OSI Approved :: MIT License
Classifier: Operating System :: MacOS
Classifier: Operating System :: Microsoft :: Windows
Classifier: Operating System :: POSIX
Classifier: Programming Language :: Python :: 3
Classifier: Programming Language :: Python :: 3.8
Classifier: Programming Language :: Python :: 3.9
Classifier: Programming Language :: Python :: 3.10
Classifier: Programming Language :: Python :: 3.11
Classifier: Topic :: Scientific/Engineering :: Artificial Intelligence
License-File: LICENSE
Requires-Dist: jax (>=0.4.1)
Requires-Dist: jaxlib (>=0.4.1)
Requires-Dist: dm-haiku
Requires-Dist: tensorflow-probability
Provides-Extra: dev
Requires-Dist: pytest (>=4) ; extra == 'dev'
Requires-Dist: pytest-cov (>=2) ; extra == 'dev'
Provides-Extra: test
Requires-Dist: pytest (>=4) ; extra == 'test'
Requires-Dist: pytest-cov (>=2) ; extra == 'test'
